<annotation>
	<folder>Desktop</folder>
	<filename>20022302140.jpg</filename>
	<source>
		<database>My Database</database>
	</source>
	<size>
		<width>960</width>
		<height>544</height>
		<depth>3</depth>
	</size>
	<segmented>0</segmented>
	<object>
		<name>smoke</name>
		<pose>Unspecified</pose>
		<truncated>0</truncated>
		<difficult>0</difficult>
		<bndbox>
			<xmin>164</xmin>
			<ymin>1</ymin>
			<xmax>443</xmax>
			<ymax>217</ymax>
		</bndbox>
	</object>
	<object>
		<name>fire</name>
		<pose>Unspecified</pose>
		<truncated>0</truncated>
		<difficult>0</difficult>
		<bndbox>
			<xmin>390</xmin>
			<ymin>377</ymin>
			<xmax>447</xmax>
			<ymax>444</ymax>
		</bndbox>
	</object>
</annotation>